doto/__init__.py
doto/__main__.py
doto/cli.py
doto/doto.py
doto/package_manager/__init__.py
doto/package_manager/_apt.py
doto/package_manager/base_package_manager.py
doto/package_manager/manager.py
dotocli-0.1.0.dist-info/LICENSE
dotocli-0.1.0.dist-info/METADATA
dotocli-0.1.0.dist-info/WHEEL
dotocli-0.1.0.dist-info/entry_points.txt
dotocli-0.1.0.dist-info/RECORD
