Metadata-Version: 2.3
Name: dotocli
Version: 0.1.0
Summary: Package Manager Utility
Author: Timur Yigit
Author-email: timur@tigitlabs.com
Requires-Python: >=3.12
Classifier: Programming Language :: Python :: 3
Classifier: Programming Language :: Python :: 3.12
Classifier: Programming Language :: Python :: 3.13
Requires-Dist: pydantic (>=2.11.7,<3.0.0)
Requires-Dist: pydantic-yaml (>=1.5.1,<2.0.0)
Requires-Dist: typer (>=0.16.0,<0.17.0)
